[
    {
      "id": "1",
      "picture": "./images/image1.jpg",
      "price": 2098,
      "name": "Sony Alpha"
    },
    {
      "id": "2",
      "picture": "./images/image2.jpg",
      "price": 2919,
      "name": "Sony Janina"
    },
    {
      "id": "3",
      "picture": "./images/image3.jpg",
      "price": 1472,
      "name": "Canon 6D"
    },
    {
      "id": "4",
      "picture": "./images/image4.jpg",
      "price": 3030,
      "name": "Canon 70D"
    },
    {
      "id": "5",
      "picture": "./images/image5.jpg",
      "price": 3593,
      "name": "Canon 1200D"
    },
    {
      "id": "6",
      "picture": "./images/image6.jpg",
      "price": 3720,
      "name": "Canon 5D"
    },
    {
      "id": "7",
      "picture": "./images/image7.jpg",
      "price": 3331,
      "name": "Sony Borolox"
    },
    {
      "id": "8",
      "picture": "./images/image8.jpg",
      "price": 2435,
      "name": "Nikon Goribz"
    },
    {
      "id": "9",
      "picture": "./images/image9.jpg",
      "price": 1223,
      "name": "Canon Konda"
    }
  ]